__init__.py
ccvag.py
ccvag-0.1.1.dist-info/LICENSE
ccvag-0.1.1.dist-info/METADATA
ccvag-0.1.1.dist-info/WHEEL
ccvag-0.1.1.dist-info/top_level.txt
ccvag-0.1.1.dist-info/RECORD
