Metadata-Version: 2.1
Name: ccvag
Version: 0.1.1
Summary: Credit Card Validator and Generator
Author-email: Kyle Sin Lynn <kylesinlynn@gmail.com>
License: Copyright (c) 2023 Kyle Sin Lynn. All rights reserved.
Project-URL: Homepage, https://github.com/kylesinlynn/luhn
Project-URL: Bug Tracker, https://github.com/kylesinlynn/luhn/issues
Classifier: Development Status :: 5 - Production/Stable
Classifier: License :: OSI Approved :: BSD License
Classifier: Natural Language :: English
Classifier: Operating System :: OS Independent
Classifier: Programming Language :: Python
Classifier: Programming Language :: Python :: 3.8
Classifier: Programming Language :: Python :: 3.9
Classifier: Programming Language :: Python :: 3.10
Classifier: Programming Language :: Python :: 3.11
Requires-Python: >=3.8
License-File: LICENSE
